pysqldict/__init__.py
pysqldict/sqldict.py
pysqldict-0.1.1.dist-info/AUTHORS.rst
pysqldict-0.1.1.dist-info/LICENSE
pysqldict-0.1.1.dist-info/METADATA
pysqldict-0.1.1.dist-info/WHEEL
pysqldict-0.1.1.dist-info/top_level.txt
pysqldict-0.1.1.dist-info/RECORD
