Metadata-Version: 2.1
Name: pysqldict
Version: 0.1.1
Summary: A library that allows python dictionaries to be stored in SQLite and provides a simple interface for read and write.
Home-page: https://github.com/charlee/pysqldict
Author: Charlee Li
Author-email: oda.charlee@gmail.com
License: MIT license
Project-URL: Changelog, https://pysqldict.readthedocs.io/en/latest/changelog.html
Project-URL: Documentation, https://pysqldict.readthedocs.io/
Project-URL: Issue Tracker, https://github.com/charlee/pysqldict/issues
Platform: UNKNOWN
Classifier: Development Status :: 5 - Production/Stable
Classifier: Intended Audience :: Developers
Classifier: License :: OSI Approved :: MIT License
Classifier: Operating System :: Unix
Classifier: Operating System :: POSIX
Classifier: Operating System :: Microsoft :: Windows
Classifier: Programming Language :: Python
Classifier: Programming Language :: Python :: 3
Classifier: Programming Language :: Python :: 3.5
Classifier: Programming Language :: Python :: 3.6
Classifier: Programming Language :: Python :: 3.7
Classifier: Programming Language :: Python :: Implementation :: CPython
Classifier: Programming Language :: Python :: Implementation :: PyPy
Classifier: Topic :: Utilities
Requires-Python: >=3.5
